optics/__init__.py
optics/calc.py
optics/nklib.py
optics/plot.py
optics/structure.py
optics/nklib_data/Ag_k.txt
optics/nklib_data/Ag_n.txt
optics/nklib_data/AlN_nk.txt
optics/nklib_data/Al_k_Rakic1998.txt
optics/nklib_data/Al_n_Rakic1998.txt
optics/nklib_data/BK7_k.txt
optics/nklib_data/BK7_n.txt
optics/nklib_data/DLC10W_extended_nk.txt
optics/nklib_data/DLC10W_nk.txt
optics/nklib_data/DLC15W_extended_nk.txt
optics/nklib_data/DLC15W_nk.txt
optics/nklib_data/DLC20W_extended_nk.txt
optics/nklib_data/DLC20W_nk.txt
optics/nklib_data/DLC3W_extended_nk.txt
optics/nklib_data/DLC3W_nk.txt
optics/nklib_data/DLC40W_extended_nk.txt
optics/nklib_data/DLC40W_nk.txt
optics/nklib_data/DLC5W_extended_nk.txt
optics/nklib_data/DLC5W_nk.txt
optics/nklib_data/DLC60W_extended_nk.txt
optics/nklib_data/DLC60W_nk.txt
optics/nklib_data/DLC80WAnode_nk.txt
optics/nklib_data/DLC_plot1.png
optics/nklib_data/DLC_plot2.png
optics/nklib_data/DLC_plot3.png
optics/nklib_data/DLC_plot4.png
optics/nklib_data/DLC_plot5.png
optics/nklib_data/DLC_plot6.png
optics/nklib_data/DLC_plot7.png
optics/nklib_data/ITO_k_Konig.txt
optics/nklib_data/ITO_n_Konig.txt
optics/nklib_data/Ni_nanowire_30f_n_para.txt
optics/nklib_data/Ni_nanowire_30f_n_perp.txt
optics/nklib_data/PDMS Refractive Index.csv
optics/nklib_data/Pd_k.txt
optics/nklib_data/Pd_n.txt
optics/nklib_data/ZnO_nk.txt
optics/support_files/ASTMG173.txt
optics/support_files/PET_extinct.txt
optics/support_files/Photopic_luminosity_function.txt
optics/support_files/glass_extinct.txt
optics/support_files/glass_extinct_assume_n1.5_depracated_for_inaccuracy.txt
optics/support_files/rgbdata.txt
optics/support_files/test_indoor.png
optics/support_files/test_outdoor.png
optics-0.0.7.dist-info/METADATA
optics-0.0.7.dist-info/WHEEL
optics-0.0.7.dist-info/top_level.txt
optics-0.0.7.dist-info/RECORD
